Programa/__init__.py
Programa/realstate_scrap.py
realstate_scrap-0.1.0.dist-info/METADATA
realstate_scrap-0.1.0.dist-info/WHEEL
realstate_scrap-0.1.0.dist-info/top_level.txt
realstate_scrap-0.1.0.dist-info/RECORD
